{
  "anonymous": false,
  "attributes": [
    {
      "name": "Autoclose",
      "values": [
        "true"
      ]
    },
    {
      "name": "Custom Submission Workflow",
      "values": [
        "Submitted"
      ]
    },
    {
      "name": "Icon",
      "values": [
        "fa-plus"
      ]
    },
    {
      "name": "Keyword",
      "values": [
        " "
      ]
    },
    {
      "name": "Redirect URL",
      "values": [
        "http://remweb.rl.gov/kinetic/DisplayPage?name=ICWO-HMIS"
      ]
    },
    {
      "name": "Survey Form Slug",
      "values": [
        "customer-satisfaction-survey"
      ]
    },
    {
      "name": "Task Assignee Team",
      "values": [
        "ICWO - Supplemental"
      ]
    },
    {
      "name": "Task Form Slug",
      "values": [
        "hanford-work-order"
      ]
    }
  ],
  "bridgedResources": [
    {
      "model": "Datastore - ICWO Approvers",
      "name": "Analyst Approver",
      "order": [

      ],
      "parameters": [
        {
          "mapping": "${values('Service Requested')}",
          "name": "Service"
        }
      ],
      "qualification": "Analyst by Service",
      "status": "Active"
    },
    {
      "model": "Datastore - ICWO Approvers",
      "name": "CAM Approver",
      "order": [

      ],
      "parameters": [
        {
          "mapping": "${values('Service Requested')}",
          "name": "Service"
        }
      ],
      "qualification": "CAM by Service",
      "status": "Active"
    },
    {
      "model": "Datastore - ICWO Approvers",
      "name": "Service Menu",
      "order": [

      ],
      "parameters": [

      ],
      "qualification": "All",
      "status": "Active"
    },
    {
      "model": "Staging DB - ICWO",
      "name": "Staging DB - ICWO - Contract ID",
      "order": [
        {
          "attribute": "Contract Release",
          "direction": "desc"
        }
      ],
      "parameters": [
        {
          "mapping": "${values('Contract')}",
          "name": "Contract ID"
        }
      ],
      "qualification": "Contract ID",
      "status": "Active"
    },
    {
      "model": "Staging DB - ICWO",
      "name": "Staging DB - ICWO - Contract ID and Release",
      "order": [

      ],
      "parameters": [
        {
          "mapping": "${values('Contract')}",
          "name": "Contract ID"
        },
        {
          "mapping": "${values('Release')}",
          "name": "Contract Release"
        }
      ],
      "qualification": "By Contract ID and Release",
      "status": "Active"
    }
  ],
  "categorizations": [
    {
      "category": {
        "slug": "inter-contractor-work-order"
      }
    }
  ],
  "customHeadContent": "",
  "description": "",
  "indexDefinitions": [
    {
      "name": "closedBy",
      "parts": [
        "closedBy"
      ],
      "unique": false
    },
    {
      "name": "createdBy",
      "parts": [
        "createdBy"
      ],
      "unique": false
    },
    {
      "name": "handle",
      "parts": [
        "handle"
      ],
      "unique": false
    },
    {
      "name": "submittedBy",
      "parts": [
        "submittedBy"
      ],
      "unique": false
    },
    {
      "name": "type,coreState,createdBy",
      "parts": [
        "type",
        "coreState",
        "createdBy"
      ],
      "unique": false
    },
    {
      "name": "type,coreState,submittedBy",
      "parts": [
        "type",
        "coreState",
        "submittedBy"
      ],
      "unique": false
    },
    {
      "name": "type,coreState,values[Requested By]",
      "parts": [
        "type",
        "coreState",
        "values[Requested By]"
      ],
      "unique": false
    },
    {
      "name": "type,coreState,values[Requested For]",
      "parts": [
        "type",
        "coreState",
        "values[Requested For]"
      ],
      "unique": false
    },
    {
      "name": "type,createdBy",
      "parts": [
        "type",
        "createdBy"
      ],
      "unique": false
    },
    {
      "name": "type,submittedBy",
      "parts": [
        "type",
        "submittedBy"
      ],
      "unique": false
    },
    {
      "name": "type,values[Requested By]",
      "parts": [
        "type",
        "values[Requested By]"
      ],
      "unique": false
    },
    {
      "name": "type,values[Requested For]",
      "parts": [
        "type",
        "values[Requested For]"
      ],
      "unique": false
    },
    {
      "name": "updatedBy",
      "parts": [
        "updatedBy"
      ],
      "unique": false
    },
    {
      "name": "values[Additional Information]",
      "parts": [
        "values[Additional Information]"
      ],
      "unique": false
    },
    {
      "name": "values[Agreement Number]",
      "parts": [
        "values[Agreement Number]"
      ],
      "unique": false
    },
    {
      "name": "values[Analyst Email]",
      "parts": [
        "values[Analyst Email]"
      ],
      "unique": false
    },
    {
      "name": "values[Analyst HID]",
      "parts": [
        "values[Analyst HID]"
      ],
      "unique": false
    },
    {
      "name": "values[Analyst Name]",
      "parts": [
        "values[Analyst Name]"
      ],
      "unique": false
    },
    {
      "name": "values[CACN]",
      "parts": [
        "values[CACN]"
      ],
      "unique": false
    },
    {
      "name": "values[CAM Email]",
      "parts": [
        "values[CAM Email]"
      ],
      "unique": false
    },
    {
      "name": "values[CAM HID]",
      "parts": [
        "values[CAM HID]"
      ],
      "unique": false
    },
    {
      "name": "values[CAM Name]",
      "parts": [
        "values[CAM Name]"
      ],
      "unique": false
    },
    {
      "name": "values[COA]",
      "parts": [
        "values[COA]"
      ],
      "unique": false
    },
    {
      "name": "values[Change in Cost Estimate]",
      "parts": [
        "values[Change in Cost Estimate]"
      ],
      "unique": false
    },
    {
      "name": "values[Change in Period of Performance]",
      "parts": [
        "values[Change in Period of Performance]"
      ],
      "unique": false
    },
    {
      "name": "values[Change in Statement of Work]",
      "parts": [
        "values[Change in Statement of Work]"
      ],
      "unique": false
    },
    {
      "name": "values[Contract Number]",
      "parts": [
        "values[Contract Number]"
      ],
      "unique": false
    },
    {
      "name": "values[Contract Release]",
      "parts": [
        "values[Contract Release]"
      ],
      "unique": false
    },
    {
      "name": "values[Contract]",
      "parts": [
        "values[Contract]"
      ],
      "unique": false
    },
    {
      "name": "values[Contractor]",
      "parts": [
        "values[Contractor]"
      ],
      "unique": false
    },
    {
      "name": "values[Current Contract Amount]",
      "parts": [
        "values[Current Contract Amount]"
      ],
      "unique": false
    },
    {
      "name": "values[Description]",
      "parts": [
        "values[Description]"
      ],
      "unique": false
    },
    {
      "name": "values[Discussion Id]",
      "parts": [
        "values[Discussion Id]"
      ],
      "unique": false
    },
    {
      "name": "values[Observing Individuals]",
      "parts": [
        "values[Observing Individuals]"
      ],
      "unique": false
    },
    {
      "name": "values[Observing Teams]",
      "parts": [
        "values[Observing Teams]"
      ],
      "unique": false
    },
    {
      "name": "values[Performing CACN]",
      "parts": [
        "values[Performing CACN]"
      ],
      "unique": false
    },
    {
      "name": "values[Period of Performance - Current End Date]",
      "parts": [
        "values[Period of Performance - Current End Date]"
      ],
      "unique": false
    },
    {
      "name": "values[Period of Performance - Current Start Date]",
      "parts": [
        "values[Period of Performance - Current Start Date]"
      ],
      "unique": false
    },
    {
      "name": "values[Period of Performance - New End Date]",
      "parts": [
        "values[Period of Performance - New End Date]"
      ],
      "unique": false
    },
    {
      "name": "values[Point of Contact Display Name]",
      "parts": [
        "values[Point of Contact Display Name]"
      ],
      "unique": false
    },
    {
      "name": "values[Point of Contact Email]",
      "parts": [
        "values[Point of Contact Email]"
      ],
      "unique": false
    },
    {
      "name": "values[Point of Contact Id]",
      "parts": [
        "values[Point of Contact Id]"
      ],
      "unique": false
    },
    {
      "name": "values[Point of Contact Phone]",
      "parts": [
        "values[Point of Contact Phone]"
      ],
      "unique": false
    },
    {
      "name": "values[Release]",
      "parts": [
        "values[Release]"
      ],
      "unique": false
    },
    {
      "name": "values[Requested By Display Name]",
      "parts": [
        "values[Requested By Display Name]"
      ],
      "unique": false
    },
    {
      "name": "values[Requested By]",
      "parts": [
        "values[Requested By]"
      ],
      "unique": false
    },
    {
      "name": "values[Requested By],values[Requested For]",
      "parts": [
        "values[Requested By]",
        "values[Requested For]"
      ],
      "unique": false
    },
    {
      "name": "values[Requested For Company]",
      "parts": [
        "values[Requested For Company]"
      ],
      "unique": false
    },
    {
      "name": "values[Requested For Display Name]",
      "parts": [
        "values[Requested For Display Name]"
      ],
      "unique": false
    },
    {
      "name": "values[Requested For Email]",
      "parts": [
        "values[Requested For Email]"
      ],
      "unique": false
    },
    {
      "name": "values[Requested For Phone]",
      "parts": [
        "values[Requested For Phone]"
      ],
      "unique": false
    },
    {
      "name": "values[Requested For]",
      "parts": [
        "values[Requested For]"
      ],
      "unique": false
    },
    {
      "name": "values[Requesting CACN]",
      "parts": [
        "values[Requesting CACN]"
      ],
      "unique": false
    },
    {
      "name": "values[Responsible Company]",
      "parts": [
        "values[Responsible Company]"
      ],
      "unique": false
    },
    {
      "name": "values[Service Requested]",
      "parts": [
        "values[Service Requested]"
      ],
      "unique": false
    },
    {
      "name": "values[Status]",
      "parts": [
        "values[Status]"
      ],
      "unique": false
    },
    {
      "name": "values[Status],createdBy",
      "parts": [
        "values[Status]",
        "createdBy"
      ],
      "unique": false
    },
    {
      "name": "values[Status],submittedBy",
      "parts": [
        "values[Status]",
        "submittedBy"
      ],
      "unique": false
    },
    {
      "name": "values[Status],values[Requested By]",
      "parts": [
        "values[Status]",
        "values[Requested By]"
      ],
      "unique": false
    },
    {
      "name": "values[Status],values[Requested For]",
      "parts": [
        "values[Status]",
        "values[Requested For]"
      ],
      "unique": false
    },
    {
      "name": "values[Supplement Amount]",
      "parts": [
        "values[Supplement Amount]"
      ],
      "unique": false
    },
    {
      "name": "values[Task Order]",
      "parts": [
        "values[Task Order]"
      ],
      "unique": false
    },
    {
      "name": "values[Total Amount]",
      "parts": [
        "values[Total Amount]"
      ],
      "unique": false
    },
    {
      "name": "values[Work Order]",
      "parts": [
        "values[Work Order]"
      ],
      "unique": false
    }
  ],
  "integrations": [

  ],
  "name": "Supplemental",
  "notes": "",
  "pages": [
    {
      "advanceCondition": null,
      "displayCondition": null,
      "displayPage": null,
      "elements": [
        {
          "type": "section",
          "renderType": null,
          "name": "Detailed Information Section",
          "title": "Detailed Information",
          "visible": false,
          "omitWhenHidden": true,
          "renderAttributes": {
            "id": "detailedInformationSection"
          },
          "elements": [
            {
              "type": "content",
              "renderType": "html",
              "name": "Detailed Information",
              "text": "  <p>Lorem ipsum dolor sit amet, consectetur adipiscing elit, sed do eiusmod tempor incididunt ut labore et dolore magna aliqua. Sollicitudin aliquam ultrices sagittis orci a scelerisque purus. Mi sit amet mauris commodo. Ornare arcu dui vivamus arcu felis bibendum ut tristique et. Orci porta non pulvinar neque. Libero id faucibus nisl tincidunt. Sed egestas egestas fringilla phasellus faucibus scelerisque eleifend donec pretium. Placerat orci nulla pellentesque dignissim enim sit. Diam ut venenatis tellus in metus vulputate eu. Amet porttitor eget dolor morbi non. Tempus quam pellentesque nec nam. Vitae justo eget magna fermentum. Aliquam vestibulum morbi blandit cursus risus at. Euismod nisi porta lorem mollis aliquam ut porttitor leo. At elementum eu facilisis sed odio morbi. Felis eget nunc lobortis mattis aliquam faucibus purus in massa. Vel pharetra vel turpis nunc eget lorem dolor sed viverra. Aenean sed adipiscing diam donec adipiscing tristique risus nec. Habitasse platea dictumst quisque sagittis purus sit. Mauris rhoncus aenean vel elit scelerisque mauris pellentesque pulvinar.</p>\n\n<p>Orci dapibus ultrices in iaculis. Massa tincidunt dui ut ornare lectus sit amet est placerat. Egestas tellus rutrum tellus pellentesque eu. Neque laoreet suspendisse interdum consectetur libero id faucibus. Elit sed vulputate mi sit amet mauris commodo quis imperdiet. Justo laoreet sit amet cursus. Sodales ut etiam sit amet. Nisl nunc mi ipsum faucibus vitae aliquet nec ullamcorper sit. Facilisi nullam vehicula ipsum a arcu cursus vitae congue. Dolor magna eget est lorem ipsum. Erat pellentesque adipiscing commodo elit at imperdiet dui accumsan. Pharetra sit amet aliquam id diam maecenas ultricies. Mi sit amet mauris commodo quis imperdiet massa tincidunt nunc. Sagittis vitae et leo duis ut diam quam nulla. Sodales ut eu sem integer vitae justo eget. Interdum posuere lorem ipsum dolor sit amet consectetur adipiscing. Arcu dui vivamus arcu felis bibendum ut tristique et. Congue eu consequat ac felis. Arcu dui vivamus arcu felis.</p>\n\n<p>Faucibus interdum posuere lorem ipsum. Aliquam etiam erat velit scelerisque in. Nisl tincidunt eget nullam non nisi. Libero volutpat sed cras ornare arcu dui vivamus arcu. Cras semper auctor neque vitae tempus. Faucibus turpis in eu mi bibendum neque egestas congue quisque. Risus nec feugiat in fermentum posuere urna nec tincidunt. Id diam vel quam elementum. Suspendisse in est ante in nibh mauris cursus mattis molestie. Nec dui nunc mattis enim ut tellus. Hendrerit dolor magna eget est lorem ipsum dolor. Faucibus ornare suspendisse sed nisi lacus. Purus sit amet volutpat consequat mauris nunc congue nisi. Lectus arcu bibendum at varius vel. Mauris pharetra et ultrices neque ornare aenean. Sit amet cursus sit amet dictum sit. At tellus at urna condimentum mattis pellentesque id nibh. Viverra mauris in aliquam sem fringilla ut morbi. Ac tincidunt vitae semper quis lectus nulla at. Rhoncus est pellentesque elit ullamcorper dignissim cras.</p>\n\n<p>Tellus pellentesque eu tincidunt tortor aliquam nulla facilisi cras fermentum. Enim diam vulputate ut pharetra sit amet. Nisi lacus sed viverra tellus in hac habitasse platea dictumst. Mauris pharetra et ultrices neque ornare aenean euismod elementum. Amet facilisis magna etiam tempor orci eu lobortis elementum. Aliquet eget sit amet tellus. Aliquam ut porttitor leo a diam. Mattis ullamcorper velit sed ullamcorper morbi. Euismod quis viverra nibh cras. In massa tempor nec feugiat. Nisl nisi scelerisque eu ultrices.</p>\n\n<p>Tempus quam pellentesque nec nam. Egestas congue quisque egestas diam in arcu cursus euismod. Eget egestas purus viverra accumsan in nisl nisi scelerisque eu. Id aliquet risus feugiat in ante metus dictum at. Viverra suspendisse potenti nullam ac tortor vitae purus faucibus ornare. Donec adipiscing tristique risus nec feugiat in fermentum posuere urna. Sit amet venenatis urna cursus. Ipsum nunc aliquet bibendum enim facilisis gravida neque. Vulputate dignissim suspendisse in est ante in nibh. Placerat vestibulum lectus mauris ultrices. Nisl pretium fusce id velit ut tortor pretium. Et odio pellentesque diam volutpat commodo sed. Nullam eget felis eget nunc. Nulla posuere sollicitudin aliquam ultrices sagittis orci a scelerisque. Eu sem integer vitae justo eget magna fermentum. In arcu cursus euismod quis.</p>",
              "visible": true,
              "renderAttributes": {
                "id": "detailedInformation",
                "style": "display:none"
              }
            }
          ]
        },
        {
          "type": "section",
          "renderType": null,
          "name": "Requested For Section",
          "title": "Request For",
          "visible": true,
          "omitWhenHidden": null,
          "renderAttributes": {
          },
          "elements": [
            {
              "type": "content",
              "renderType": "html",
              "name": "Requested For Container",
              "text": null,
              "visible": true,
              "renderAttributes": {
                "id": "requestedFor"
              }
            }
          ]
        },
        {
          "type": "section",
          "renderType": null,
          "name": "Billing Section",
          "title": "Billing Information",
          "visible": false,
          "omitWhenHidden": true,
          "renderAttributes": {
          },
          "elements": [
            {
              "type": "content",
              "renderType": "html",
              "name": "Billing Container",
              "text": null,
              "visible": true,
              "renderAttributes": {
                "id": "billingInformation"
              }
            }
          ]
        },
        {
          "type": "section",
          "renderType": null,
          "name": "Point of Contact Section",
          "title": "Point of Contact",
          "visible": false,
          "omitWhenHidden": true,
          "renderAttributes": {
          },
          "elements": [
            {
              "type": "content",
              "renderType": "html",
              "name": "Point of Contact Container",
              "text": null,
              "visible": true,
              "renderAttributes": {
                "id": "pointOfContact"
              }
            }
          ]
        },
        {
          "type": "section",
          "renderType": null,
          "name": "Request Details Section 1",
          "title": "Request Details",
          "visible": true,
          "omitWhenHidden": null,
          "renderAttributes": {
            "class": "w-50"
          },
          "elements": [
            {
              "enabled": true,
              "dataType": "string",
              "requiredMessage": null,
              "name": "Contractor",
              "choicesResourceName": null,
              "omitWhenHidden": null,
              "renderAttributes": {
              },
              "renderType": "dropdown",
              "pattern": null,
              "defaultValue": null,
              "visible": true,
              "choices": [
                {
                  "label": "BNI",
                  "value": "BNI"
                },
                {
                  "label": "CHPRC Closeout",
                  "value": "CHPRC Closeout"
                },
                {
                  "label": "CPCC",
                  "value": "CPCC"
                },
                {
                  "label": "HLMI",
                  "value": "HLMI"
                },
                {
                  "label": "HPM",
                  "value": "HPM"
                },
                {
                  "label": "MSA Closeout",
                  "value": "MSA Closeout"
                },
                {
                  "label": "PNNL",
                  "value": "PNNL"
                },
                {
                  "label": "WAI Closeout",
                  "value": "WAI Closeout"
                },
                {
                  "label": "WRPS",
                  "value": "WRPS"
                }
              ],
              "label": "Contractor",
              "choicesRunIf": null,
              "constraints": [

              ],
              "events": [

              ],
              "defaultResourceName": null,
              "type": "field",
              "key": "f910",
              "required": true
            },
            {
              "enabled": true,
              "dataType": "string",
              "requiredMessage": null,
              "name": "Service Requested",
              "choicesResourceName": "Service Menu",
              "omitWhenHidden": true,
              "renderAttributes": {
              },
              "renderType": "dropdown",
              "pattern": null,
              "defaultValue": null,
              "visible": "values('Contractor') == \"BNI\" || values('Contractor') == \"HLMI\" || values('Contractor') == \"HPM\" || values('Contractor') == \"PNNL\" || values('Contractor') == \"WAI Closeout\"",
              "choices": {
                "label": "${resources('Service Menu:Service')}",
                "value": "${resources('Service Menu:Service')}"
              },
              "label": "Service Requested",
              "choicesRunIf": null,
              "constraints": [

              ],
              "events": [
                {
                  "name": "Set CAM",
                  "type": "Change",
                  "action": "Set Fields",
                  "mappings": [
                    {
                      "field": "CAM Name",
                      "value": "${resources('CAM Approver:Name')}",
                      "visible": true
                    },
                    {
                      "field": "CAM HID",
                      "value": "${resources('CAM Approver:HID')}",
                      "visible": true
                    },
                    {
                      "field": "CAM Email",
                      "value": "${resources('CAM Approver:Email')}",
                      "visible": true
                    }
                  ],
                  "bridgedResourceName": "CAM Approver"
                },
                {
                  "name": "Set Analyst",
                  "type": "Change",
                  "action": "Set Fields",
                  "mappings": [
                    {
                      "field": "Analyst Name",
                      "value": "${resources('Analyst Approver:Name')}",
                      "visible": true
                    },
                    {
                      "field": "Analyst HID",
                      "value": "${resources('Analyst Approver:HID')}",
                      "visible": true
                    },
                    {
                      "field": "Analyst Email",
                      "value": "${resources('Analyst Approver:Email')}",
                      "visible": true
                    }
                  ],
                  "bridgedResourceName": "Analyst Approver"
                }
              ],
              "defaultResourceName": null,
              "type": "field",
              "key": "f911",
              "required": false
            },
            {
              "enabled": true,
              "dataType": "string",
              "requiredMessage": null,
              "name": "Task Order",
              "omitWhenHidden": true,
              "renderAttributes": {
              },
              "renderType": "text",
              "pattern": null,
              "defaultValue": null,
              "visible": "values('Contractor') == \"BNI\" ",
              "label": "Task Order",
              "constraints": [

              ],
              "events": [

              ],
              "rows": 1,
              "defaultResourceName": null,
              "type": "field",
              "key": "f913",
              "required": false
            },
            {
              "enabled": true,
              "dataType": "string",
              "requiredMessage": null,
              "name": "Agreement Number",
              "omitWhenHidden": true,
              "renderAttributes": {
              },
              "renderType": "text",
              "pattern": null,
              "defaultValue": null,
              "visible": " values('Contractor') == \"HPM\"",
              "label": "Agreement Number",
              "constraints": [

              ],
              "events": [

              ],
              "rows": 1,
              "defaultResourceName": null,
              "type": "field",
              "key": "f917",
              "required": false
            },
            {
              "enabled": true,
              "dataType": "string",
              "requiredMessage": null,
              "name": "Contract Number",
              "omitWhenHidden": true,
              "renderAttributes": {
              },
              "renderType": "text",
              "pattern": null,
              "defaultValue": null,
              "visible": "values('Contractor')==\"PNNL\"",
              "label": "Contract Number",
              "constraints": [

              ],
              "events": [

              ],
              "rows": 1,
              "defaultResourceName": null,
              "type": "field",
              "key": "f918",
              "required": false
            },
            {
              "enabled": true,
              "dataType": "string",
              "requiredMessage": null,
              "name": "Work Order",
              "omitWhenHidden": true,
              "renderAttributes": {
              },
              "renderType": "text",
              "pattern": null,
              "defaultValue": null,
              "visible": "values('Contractor') == \"HLMI\" || values('Contractor') == \"WAI Closeout\"",
              "label": "Work Order",
              "constraints": [

              ],
              "events": [

              ],
              "rows": 1,
              "defaultResourceName": null,
              "type": "field",
              "key": "f934",
              "required": false
            }
          ]
        },
        {
          "type": "section",
          "renderType": null,
          "name": "Contract Lookup Section",
          "title": null,
          "visible": "values('Contractor')==\"CHPRC Closeout\" || values('Contractor')==\"CPCC\" || values('Contractor')==\"MSA Closeout\" || values('Contractor')==\"WRPS\"",
          "omitWhenHidden": true,
          "renderAttributes": {
            "class": "w-50"
          },
          "elements": [
            {
              "type": "content",
              "renderType": "html",
              "name": "Lookup Instructions",
              "text": "<p>Enter the Contract and/or Release and click \"Lookup ICWO\".<br>\nOn the resulting table, click on the correct entry to populate form fields.</p>",
              "visible": true,
              "renderAttributes": {
              }
            },
            {
              "enabled": true,
              "dataType": "string",
              "requiredMessage": null,
              "name": "Contract",
              "omitWhenHidden": true,
              "renderAttributes": {
              },
              "renderType": "text",
              "pattern": null,
              "defaultValue": null,
              "visible": "values('Contractor')==\"CHPRC Closeout\" || values('Contractor')==\"CPCC\" || values('Contractor')==\"MSA Closeout\" || values('Contractor')==\"WRPS\"",
              "label": "Contract",
              "constraints": [

              ],
              "events": [

              ],
              "rows": 1,
              "defaultResourceName": null,
              "type": "field",
              "key": "f915",
              "required": false
            },
            {
              "enabled": true,
              "dataType": "string",
              "requiredMessage": null,
              "name": "Release",
              "omitWhenHidden": null,
              "renderAttributes": {
              },
              "renderType": "text",
              "pattern": null,
              "defaultValue": null,
              "visible": true,
              "label": "Release",
              "constraints": [

              ],
              "events": [

              ],
              "rows": 1,
              "defaultResourceName": null,
              "type": "field",
              "key": "f916",
              "required": false
            },
            {
              "type": "button",
              "label": "Lookup ICWO",
              "name": "Lookup ICWO",
              "visible": true,
              "enabled": true,
              "renderType": "custom",
              "renderAttributes": {
              },
              "events": [
                {
                  "name": "Lookup Contract",
                  "type": "Click",
                  "action": "Custom",
                  "code": "      // Get values from JSON Order Data field\n      searchConfig.contractTable.response = resource;\n      // Load the Table with the values.\n      DataViewer.renderResults( $(K('content[Contract Container]').element()), searchConfig.contractTable );\n   ",
                  "bridgedResourceName": "Staging DB - ICWO - Contract ID",
                  "runIf": "values('Release')==null"
                },
                {
                  "name": "Lookup Contract and Release",
                  "type": "Click",
                  "action": "Custom",
                  "code": "      // Get values from JSON Order Data field\n      searchConfig.contractTable.response = resource;\n      // Load the Table with the values.\n      DataViewer.renderResults( $(K('content[Contract Container]').element()), searchConfig.contractTable );",
                  "runIf": "values('Release')!=null",
                  "bridgedResourceName": "Staging DB - ICWO - Contract ID and Release"
                }
              ]
            },
            {
              "type": "content",
              "renderType": "html",
              "name": "Spacer 1",
              "text": "<p>\n</p>",
              "visible": true,
              "renderAttributes": {
              }
            },
            {
              "type": "content",
              "renderType": "html",
              "name": "Contract Container",
              "text": null,
              "visible": true,
              "renderAttributes": {
              }
            },
            {
              "enabled": true,
              "dataType": "string",
              "requiredMessage": null,
              "name": "Contract Release",
              "omitWhenHidden": null,
              "renderAttributes": {
              },
              "renderType": "text",
              "pattern": null,
              "defaultValue": null,
              "visible": true,
              "label": "Contract Release",
              "constraints": [

              ],
              "events": [

              ],
              "rows": 1,
              "defaultResourceName": null,
              "type": "field",
              "key": "f935",
              "required": false
            }
          ]
        },
        {
          "type": "section",
          "renderType": null,
          "name": "Request Details Section 2",
          "title": "",
          "visible": true,
          "omitWhenHidden": null,
          "renderAttributes": {
            "class": "w-50"
          },
          "elements": [
            {
              "enabled": true,
              "dataType": "string",
              "requiredMessage": null,
              "name": "Requesting CACN",
              "omitWhenHidden": true,
              "renderAttributes": {
              },
              "renderType": "text",
              "pattern": null,
              "defaultValue": null,
              "visible": "values('Contractor')==\"CHPRC Closeout\" || values('Contractor')==\"CPCC\" || values('Contractor')==\"MSA Closeout\" || values('Contractor')==\"WRPS\"",
              "label": "Requesting CACN",
              "constraints": [

              ],
              "events": [

              ],
              "rows": 1,
              "defaultResourceName": null,
              "type": "field",
              "key": "f929",
              "required": false
            },
            {
              "enabled": true,
              "dataType": "string",
              "requiredMessage": null,
              "name": "Performing CACN",
              "omitWhenHidden": null,
              "renderAttributes": {
              },
              "renderType": "text",
              "pattern": null,
              "defaultValue": null,
              "visible": true,
              "label": "Performing CACN",
              "constraints": [

              ],
              "events": [

              ],
              "rows": 1,
              "defaultResourceName": null,
              "type": "field",
              "key": "f919",
              "required": false
            },
            {
              "enabled": true,
              "dataType": "string",
              "requiredMessage": null,
              "name": "Description",
              "omitWhenHidden": true,
              "renderAttributes": {
              },
              "renderType": "text",
              "pattern": null,
              "defaultValue": null,
              "visible": "values('Contractor')==\"CHPRC Closeout\" || values('Contractor')==\"CPCC\" || values('Contractor')==\"MSA Closeout\" || values('Contractor')==\"WRPS\"",
              "label": "Description",
              "constraints": [

              ],
              "events": [

              ],
              "rows": 4,
              "defaultResourceName": null,
              "type": "field",
              "key": "f930",
              "required": false
            },
            {
              "enabled": true,
              "dataType": "string",
              "requiredMessage": null,
              "name": "Current Contract Amount",
              "omitWhenHidden": null,
              "renderAttributes": {
              },
              "renderType": "text",
              "pattern": null,
              "defaultValue": null,
              "visible": true,
              "label": "Current Contract Amount",
              "constraints": [

              ],
              "events": [
                {
                  "name": "Set Total",
                  "type": "Change",
                  "action": "Set Fields",
                  "mappings": [
                    {
                      "field": "Total Amount",
                      "value": "${values('Current Contract Amount')}",
                      "visible": null
                    }
                  ]
                }
              ],
              "rows": 1,
              "defaultResourceName": null,
              "type": "field",
              "key": "f931",
              "required": false
            },
            {
              "enabled": true,
              "dataType": "string",
              "requiredMessage": null,
              "name": "Supplement Amount",
              "omitWhenHidden": null,
              "renderAttributes": {
              },
              "renderType": "text",
              "pattern": null,
              "defaultValue": null,
              "visible": true,
              "label": "Supplement Amount",
              "constraints": [

              ],
              "events": [
                {
                  "name": "Add Total",
                  "type": "Change",
                  "action": "Custom",
                  "mappings": [
                    {
                      "field": "Total Amount",
                      "value": "${values('Current Contract Amount')} + ${values('Supplement Amount')}",
                      "visible": null
                    }
                  ],
                  "code": "total = (parseFloat (K('field[Current Contract Amount]').value()) + parseFloat (K('field[Supplement Amount]').value())).toFixed(2)\nK('field[Total Amount]').value(total)"
                }
              ],
              "rows": 1,
              "defaultResourceName": null,
              "type": "field",
              "key": "f932",
              "required": false
            },
            {
              "enabled": true,
              "dataType": "string",
              "requiredMessage": null,
              "name": "Total Amount",
              "omitWhenHidden": null,
              "renderAttributes": {
              },
              "renderType": "text",
              "pattern": null,
              "defaultValue": null,
              "visible": true,
              "label": "Total Amount",
              "constraints": [

              ],
              "events": [

              ],
              "rows": 1,
              "defaultResourceName": null,
              "type": "field",
              "key": "f933",
              "required": false
            },
            {
              "enabled": true,
              "dataType": "string",
              "requiredMessage": null,
              "name": "Period of Performance - Current Start Date",
              "omitWhenHidden": null,
              "renderAttributes": {
              },
              "renderType": "date",
              "pattern": null,
              "defaultValue": null,
              "visible": true,
              "label": "Period of Performance - Start Date",
              "constraints": [

              ],
              "events": [

              ],
              "defaultResourceName": null,
              "type": "field",
              "key": "f920",
              "required": false
            },
            {
              "enabled": true,
              "dataType": "string",
              "requiredMessage": null,
              "name": "Period of Performance - Current End Date",
              "omitWhenHidden": null,
              "renderAttributes": {
              },
              "renderType": "date",
              "pattern": null,
              "defaultValue": null,
              "visible": true,
              "label": "Period of Performance - Current End Date",
              "constraints": [

              ],
              "events": [

              ],
              "defaultResourceName": null,
              "type": "field",
              "key": "f921",
              "required": false
            },
            {
              "enabled": true,
              "dataType": "string",
              "requiredMessage": null,
              "name": "Change in Period of Performance",
              "choicesResourceName": null,
              "omitWhenHidden": null,
              "renderAttributes": {
              },
              "renderType": "radio",
              "pattern": null,
              "defaultValue": null,
              "visible": true,
              "choices": [
                {
                  "label": "Yes",
                  "value": "Yes"
                },
                {
                  "label": "No",
                  "value": "No"
                }
              ],
              "label": "Change in Period of Performance?",
              "choicesRunIf": null,
              "constraints": [

              ],
              "events": [

              ],
              "defaultResourceName": null,
              "type": "field",
              "key": "f925",
              "required": false
            },
            {
              "enabled": true,
              "dataType": "string",
              "requiredMessage": null,
              "name": "Period of Performance - New End Date",
              "omitWhenHidden": true,
              "renderAttributes": {
              },
              "renderType": "date",
              "pattern": null,
              "defaultValue": null,
              "visible": "values('Change in Period of Performance')===\"Yes\"",
              "label": "Period of Performance - New End Date",
              "constraints": [

              ],
              "events": [

              ],
              "defaultResourceName": null,
              "type": "field",
              "key": "f924",
              "required": false
            },
            {
              "enabled": true,
              "dataType": "string",
              "requiredMessage": null,
              "name": "Change in Statement of Work",
              "choicesResourceName": null,
              "omitWhenHidden": null,
              "renderAttributes": {
              },
              "renderType": "radio",
              "pattern": null,
              "defaultValue": null,
              "visible": true,
              "choices": [
                {
                  "label": "Yes",
                  "value": "Yes"
                },
                {
                  "label": "No",
                  "value": "No"
                }
              ],
              "label": "Change in Statement of Work?",
              "choicesRunIf": null,
              "constraints": [

              ],
              "events": [

              ],
              "defaultResourceName": null,
              "type": "field",
              "key": "f926",
              "required": false
            },
            {
              "type": "content",
              "renderType": "html",
              "name": "Statement of Work Note",
              "text": "<p>Please attach the updated Statement of Work to this request.</p>",
              "visible": "values('Change in Statement of Work')===\"Yes\"",
              "renderAttributes": {
              }
            },
            {
              "enabled": true,
              "dataType": "string",
              "requiredMessage": null,
              "name": "Change in Cost Estimate",
              "choicesResourceName": null,
              "omitWhenHidden": null,
              "renderAttributes": {
              },
              "renderType": "radio",
              "pattern": null,
              "defaultValue": null,
              "visible": true,
              "choices": [
                {
                  "label": "Yes",
                  "value": "Yes"
                },
                {
                  "label": "No",
                  "value": "No"
                }
              ],
              "label": "Change in Cost Estimate?",
              "choicesRunIf": null,
              "constraints": [

              ],
              "events": [

              ],
              "defaultResourceName": null,
              "type": "field",
              "key": "f928",
              "required": false
            },
            {
              "type": "content",
              "renderType": "html",
              "name": "Cost Estimate Note",
              "text": "<p>Please attach the updated Cost Estimate to this request.</p>",
              "visible": "values('Change in Cost Estimate')===\"Yes\"",
              "renderAttributes": {
              }
            },
            {
              "enabled": true,
              "dataType": "string",
              "requiredMessage": null,
              "name": "Additional Information",
              "omitWhenHidden": null,
              "renderAttributes": {
              },
              "renderType": "text",
              "pattern": null,
              "defaultValue": null,
              "visible": true,
              "label": "Additional Information",
              "constraints": [

              ],
              "events": [

              ],
              "rows": 4,
              "defaultResourceName": null,
              "type": "field",
              "key": "f922",
              "required": false
            },
            {
              "enabled": true,
              "dataType": "string",
              "requiredMessage": null,
              "name": "Analyst HID",
              "omitWhenHidden": null,
              "renderAttributes": {
              },
              "renderType": "text",
              "pattern": null,
              "defaultValue": null,
              "visible": true,
              "label": "Analyst HID",
              "constraints": [

              ],
              "events": [

              ],
              "rows": 1,
              "defaultResourceName": null,
              "type": "field",
              "key": "f937",
              "required": false
            },
            {
              "enabled": false,
              "dataType": "string",
              "requiredMessage": null,
              "name": "Analyst Name",
              "omitWhenHidden": null,
              "renderAttributes": {
              },
              "renderType": "text",
              "pattern": null,
              "defaultValue": null,
              "visible": true,
              "label": "Analyst Name",
              "constraints": [

              ],
              "events": [

              ],
              "rows": 1,
              "defaultResourceName": null,
              "type": "field",
              "key": "f936",
              "required": false
            },
            {
              "enabled": true,
              "dataType": "string",
              "requiredMessage": null,
              "name": "Analyst Email",
              "omitWhenHidden": null,
              "renderAttributes": {
              },
              "renderType": "text",
              "pattern": null,
              "defaultValue": null,
              "visible": true,
              "label": "Analyst Email",
              "constraints": [

              ],
              "events": [

              ],
              "rows": 1,
              "defaultResourceName": null,
              "type": "field",
              "key": "f941",
              "required": false
            },
            {
              "enabled": true,
              "dataType": "string",
              "requiredMessage": null,
              "name": "CAM HID",
              "omitWhenHidden": null,
              "renderAttributes": {
              },
              "renderType": "text",
              "pattern": null,
              "defaultValue": null,
              "visible": true,
              "label": "CAM HID",
              "constraints": [

              ],
              "events": [

              ],
              "rows": 1,
              "defaultResourceName": null,
              "type": "field",
              "key": "f939",
              "required": false
            },
            {
              "enabled": false,
              "dataType": "string",
              "requiredMessage": null,
              "name": "CAM Name",
              "omitWhenHidden": null,
              "renderAttributes": {
              },
              "renderType": "text",
              "pattern": null,
              "defaultValue": null,
              "visible": true,
              "label": "CAM Name",
              "constraints": [

              ],
              "events": [

              ],
              "rows": 1,
              "defaultResourceName": null,
              "type": "field",
              "key": "f938",
              "required": false
            },
            {
              "enabled": true,
              "dataType": "string",
              "requiredMessage": null,
              "name": "CAM Email",
              "omitWhenHidden": null,
              "renderAttributes": {
              },
              "renderType": "text",
              "pattern": null,
              "defaultValue": null,
              "visible": true,
              "label": "CAM Email",
              "constraints": [

              ],
              "events": [

              ],
              "rows": 1,
              "defaultResourceName": null,
              "type": "field",
              "key": "f940",
              "required": false
            },
            {
              "enabled": true,
              "dataType": "file",
              "requiredMessage": null,
              "name": "Attachments",
              "omitWhenHidden": null,
              "renderAttributes": {
              },
              "renderType": "attachment",
              "pattern": null,
              "defaultValue": null,
              "visible": true,
              "label": "Attachments",
              "constraints": [

              ],
              "allowMultiple": true,
              "events": [

              ],
              "defaultResourceName": null,
              "type": "field",
              "key": "f923",
              "required": false
            }
          ]
        },
        {
          "type": "button",
          "label": "Submit",
          "name": "Submit Button",
          "visible": true,
          "enabled": true,
          "renderType": "submit-page",
          "renderAttributes": {
          }
        },
        {
          "type": "section",
          "renderType": null,
          "name": "Hidden Section",
          "title": "Hidden Section",
          "visible": false,
          "omitWhenHidden": false,
          "renderAttributes": {
          },
          "elements": [
            {
              "enabled": true,
              "dataType": "string",
              "requiredMessage": null,
              "name": "Requested For Email",
              "omitWhenHidden": null,
              "renderAttributes": {
              },
              "renderType": "text",
              "pattern": null,
              "defaultValue": null,
              "visible": true,
              "label": "Requested For Email",
              "constraints": [

              ],
              "events": [

              ],
              "rows": 1,
              "defaultResourceName": null,
              "type": "field",
              "key": "f3",
              "required": false
            },
            {
              "enabled": true,
              "dataType": "string",
              "requiredMessage": null,
              "name": "Requested For Phone",
              "omitWhenHidden": null,
              "renderAttributes": {
              },
              "renderType": "text",
              "pattern": null,
              "defaultValue": null,
              "visible": true,
              "label": "Requested For Phone",
              "constraints": [

              ],
              "events": [

              ],
              "rows": 1,
              "defaultResourceName": null,
              "type": "field",
              "key": "f2",
              "required": false
            },
            {
              "enabled": true,
              "dataType": "string",
              "requiredMessage": null,
              "name": "Requested For Company",
              "omitWhenHidden": null,
              "renderAttributes": {
              },
              "renderType": "text",
              "pattern": null,
              "defaultValue": null,
              "visible": true,
              "label": "Requested For Company",
              "constraints": [

              ],
              "events": [

              ],
              "rows": 1,
              "defaultResourceName": null,
              "type": "field",
              "key": "f12",
              "required": false
            },
            {
              "enabled": true,
              "dataType": "string",
              "requiredMessage": null,
              "name": "Responsible Company",
              "omitWhenHidden": null,
              "renderAttributes": {
              },
              "renderType": "text",
              "pattern": null,
              "defaultValue": null,
              "visible": true,
              "label": "Responsible Company",
              "constraints": [

              ],
              "events": [

              ],
              "rows": 1,
              "defaultResourceName": null,
              "type": "field",
              "key": "f13",
              "required": false
            },
            {
              "enabled": true,
              "dataType": "string",
              "requiredMessage": null,
              "name": "Point of Contact Display Name",
              "omitWhenHidden": null,
              "renderAttributes": {
              },
              "renderType": "text",
              "pattern": null,
              "defaultValue": null,
              "visible": true,
              "label": "Point of Contact Display Name",
              "constraints": [

              ],
              "events": [

              ],
              "rows": 1,
              "defaultResourceName": null,
              "type": "field",
              "key": "f10",
              "required": false
            },
            {
              "enabled": true,
              "dataType": "string",
              "requiredMessage": null,
              "name": "Point of Contact Id",
              "omitWhenHidden": null,
              "renderAttributes": {
              },
              "renderType": "text",
              "pattern": null,
              "defaultValue": null,
              "visible": true,
              "label": "Point of Contact Id",
              "constraints": [

              ],
              "events": [

              ],
              "rows": 1,
              "defaultResourceName": null,
              "type": "field",
              "key": "f11",
              "required": false
            },
            {
              "enabled": true,
              "dataType": "string",
              "requiredMessage": null,
              "name": "Point of Contact Email",
              "omitWhenHidden": null,
              "renderAttributes": {
              },
              "renderType": "text",
              "pattern": null,
              "defaultValue": null,
              "visible": true,
              "label": "Point of Contact Email",
              "constraints": [

              ],
              "events": [

              ],
              "rows": 1,
              "defaultResourceName": null,
              "type": "field",
              "key": "f14",
              "required": false
            },
            {
              "enabled": true,
              "dataType": "string",
              "requiredMessage": null,
              "name": "Point of Contact Phone",
              "omitWhenHidden": null,
              "renderAttributes": {
              },
              "renderType": "text",
              "pattern": null,
              "defaultValue": null,
              "visible": true,
              "label": "Point of Contact Phone",
              "constraints": [

              ],
              "events": [

              ],
              "rows": 1,
              "defaultResourceName": null,
              "type": "field",
              "key": "f15",
              "required": false
            },
            {
              "enabled": true,
              "dataType": "string",
              "requiredMessage": null,
              "name": "CACN",
              "omitWhenHidden": null,
              "renderAttributes": {
              },
              "renderType": "text",
              "pattern": null,
              "defaultValue": null,
              "visible": true,
              "label": "CACN",
              "constraints": [

              ],
              "events": [

              ],
              "rows": 1,
              "defaultResourceName": null,
              "type": "field",
              "key": "f5",
              "required": false
            },
            {
              "enabled": true,
              "dataType": "string",
              "requiredMessage": null,
              "name": "COA",
              "omitWhenHidden": null,
              "renderAttributes": {
              },
              "renderType": "text",
              "pattern": null,
              "defaultValue": null,
              "visible": true,
              "label": "COA",
              "constraints": [

              ],
              "events": [

              ],
              "rows": 1,
              "defaultResourceName": null,
              "type": "field",
              "key": "f6",
              "required": false
            },
            {
              "type": "section",
              "renderType": null,
              "name": "Hidden System Questions Do Not Delete",
              "title": "Hidden System Questions Do Not Delete",
              "visible": false,
              "omitWhenHidden": false,
              "renderAttributes": {
              },
              "elements": [
                {
                  "enabled": true,
                  "dataType": "string",
                  "requiredMessage": null,
                  "name": "Requested For",
                  "omitWhenHidden": null,
                  "renderAttributes": {
                  },
                  "renderType": "text",
                  "pattern": null,
                  "defaultValue": "${identity('username')}",
                  "visible": true,
                  "label": "Requested For",
                  "constraints": [

                  ],
                  "events": [

                  ],
                  "rows": 1,
                  "defaultResourceName": null,
                  "type": "field",
                  "key": "f908",
                  "required": false
                },
                {
                  "enabled": true,
                  "dataType": "string",
                  "requiredMessage": null,
                  "name": "Requested For Display Name",
                  "omitWhenHidden": null,
                  "renderAttributes": {
                  },
                  "renderType": "text",
                  "pattern": null,
                  "defaultValue": "${identity('displayName')}",
                  "visible": true,
                  "label": "Requested For Display Name",
                  "constraints": [

                  ],
                  "events": [

                  ],
                  "rows": 1,
                  "defaultResourceName": null,
                  "type": "field",
                  "key": "f909",
                  "required": false
                },
                {
                  "enabled": true,
                  "dataType": "string",
                  "requiredMessage": null,
                  "name": "Requested By",
                  "omitWhenHidden": null,
                  "renderAttributes": {
                  },
                  "renderType": "text",
                  "pattern": null,
                  "defaultValue": "${identity('username')}",
                  "visible": true,
                  "label": "Requested By",
                  "constraints": [

                  ],
                  "events": [

                  ],
                  "rows": 1,
                  "defaultResourceName": null,
                  "type": "field",
                  "key": "f906",
                  "required": false
                },
                {
                  "enabled": true,
                  "dataType": "string",
                  "requiredMessage": null,
                  "name": "Requested By Display Name",
                  "omitWhenHidden": null,
                  "renderAttributes": {
                  },
                  "renderType": "text",
                  "pattern": null,
                  "defaultValue": "${identity('displayName')}",
                  "visible": true,
                  "label": "Requested By Display Name",
                  "constraints": [

                  ],
                  "events": [

                  ],
                  "rows": 1,
                  "defaultResourceName": null,
                  "type": "field",
                  "key": "f907",
                  "required": false
                },
                {
                  "enabled": true,
                  "dataType": "string",
                  "requiredMessage": null,
                  "name": "Discussion Id",
                  "omitWhenHidden": null,
                  "renderAttributes": {
                  },
                  "renderType": "text",
                  "pattern": null,
                  "defaultValue": null,
                  "visible": true,
                  "label": "Discussion Id",
                  "constraints": [

                  ],
                  "events": [

                  ],
                  "rows": 1,
                  "defaultResourceName": null,
                  "type": "field",
                  "key": "f902",
                  "required": false
                },
                {
                  "enabled": true,
                  "dataType": "json",
                  "requiredMessage": null,
                  "name": "Observing Teams",
                  "choicesResourceName": null,
                  "omitWhenHidden": null,
                  "renderAttributes": {
                  },
                  "renderType": "checkbox",
                  "pattern": null,
                  "defaultValue": null,
                  "visible": true,
                  "choices": [

                  ],
                  "label": "Observing Teams",
                  "choicesRunIf": null,
                  "constraints": [

                  ],
                  "events": [

                  ],
                  "defaultResourceName": null,
                  "type": "field",
                  "key": "f904",
                  "required": false
                },
                {
                  "enabled": true,
                  "dataType": "json",
                  "requiredMessage": null,
                  "name": "Observing Individuals",
                  "choicesResourceName": null,
                  "omitWhenHidden": null,
                  "renderAttributes": {
                  },
                  "renderType": "checkbox",
                  "pattern": null,
                  "defaultValue": null,
                  "visible": true,
                  "choices": [

                  ],
                  "label": "Observing Individuals",
                  "choicesRunIf": null,
                  "constraints": [

                  ],
                  "events": [

                  ],
                  "defaultResourceName": null,
                  "type": "field",
                  "key": "f905",
                  "required": false
                },
                {
                  "enabled": true,
                  "dataType": "string",
                  "requiredMessage": null,
                  "name": "Status",
                  "omitWhenHidden": null,
                  "renderAttributes": {
                  },
                  "renderType": "text",
                  "pattern": null,
                  "defaultValue": "Draft",
                  "visible": true,
                  "label": "Status",
                  "constraints": [

                  ],
                  "events": [

                  ],
                  "rows": 1,
                  "defaultResourceName": null,
                  "type": "field",
                  "key": "f901",
                  "required": false
                }
              ]
            }
          ]
        }
      ],
      "events": [
        {
          "name": "Load Requested For",
          "type": "Load",
          "action": "Custom",
          "code": "// ***** CONFIGURE *********\nvar load = {\n\t//Form to Load\n  \"formSlug\":\"requested-for-search\", \n  //Container for the form (jQuery syntax)\n  \"container\": '#requestedFor', \n  //Define values to pass into subform.  Map subform Field to value or K('field') reference.\n\t//NOTE: INCLUDE THESE FIELDS IN SUBFORM, OR PAGE WILL NOT LOAD\n  \"paramsInput\": {\n    \"Requested For Display Name\": K('field[Requested For Display Name]').value(),\n    \"Review Mode\": K('form').reviewMode() ? true : \"\",\n    \"Request For\": K('field[Requested For]').value() != null && K('identity').username != K('field[Requested For]').value()? \"Someone Else\" : \"Me\",\n    \"Email\": K('field[Requested For Email]').value(),\n    \"Phone\": K('field[Requested For Phone]').value(),\n    \"Company\":  K('field[Requested For Company]').value(),\n    \"Responsible Company\":K('field[Responsible Company]').value(),\n\t},\n  //Define Fields to set on parent form using watch.  Map subform field to parent form field.\n  \"watchFields\":{\n    \"Requested For Id\": \"Requested For\",\n    \"Requested For Display Name\": \"Requested For Display Name\",\n    \"Email\": \"Requested For Email\",\n    \"Phone\": \"Requested For Phone\",\n    \"Company\":  \"Requested For Company\",\n    \"Responsible Company\": \"Responsible Company\",\n  }\n}\n// ***** END CONFIGURE *********\n\n// Turn paramsInput into formatted/encoded urlParams array as that's what's required by the\n// Kinetic App when passing in values\nload.urlParams = [];\n$.each( load.paramsInput, function( key, value ){\n  load.urlParams.push( \"values[\" + encodeURIComponent( key ) + \"]=\" + encodeURIComponent( value ) );\n})\n\n\n// Remove null values from urlParams list\nload.urlParams = load.urlParams.filter(function(val) { return val.split(\"=\")[1]!==\"null\" });\n\n// Load the Subform\nK.load({\n  path: bundle.spaceLocation() + '/'+ K(\"kapp\").slug()+ '/' + load.formSlug + '?' + load.urlParams.join(\"&\"),\n  container: load.container,\n  parent: K('form'),\n  loaded: function(form) {\n    // initialize watch fields definfed in configuration\n\t\t$.each(load.watchFields, function(source, desination){\n\t\t  form.$watch(source, function(newVal,oldVal){\n        K('field['+desination+']').value(newVal);\n      });\n    })\n  }\n});"
        },
        {
          "name": "Load Point of Contact",
          "type": "Load",
          "action": "Custom",
          "code": "// ***** CONFIGURE *********\nvar load = {\n\t//Form to Load\n  \"formSlug\":\"person-search\", \n  //Container for the form (jQuery syntax)\n  \"container\": '#pointOfContact', \n  //Define values to pass into subform.  Map subform Field to value or K('field') reference.\n\t//NOTE: INCLUDE THESE FIELDS IN SUBFORM, OR PAGE WILL NOT LOAD\n  \"paramsInput\": {\n    \"Display Name\": K('field[Point of Contact Display Name]').value(),\n    \"Review Mode\": K('form').reviewMode() ? true : \"\",\n    \"Id\": K('field[Point of Contact Id]').value(),\n    \"Email\": K('field[Point of Contact Email]').value(),\n    \"Phone\": K('field[Point of Contact Phone]').value(),\n\t},\n  //Define Fields to set on parent form using watch.  Map subform field to parent form field.\n  \"watchFields\":{\n    \"Id\": \"Point of Contact Id\",\n    \"Display Name\": \"Point of Contact Display Name\",\n    \"Email\": \"Point of Contact Email\",\n    \"Phone\": \"Point of Contact Phone\",\n  }\n}\n// ***** END CONFIGURE *********\n\n// Turn paramsInput into formatted/encoded urlParams array as that's what's required by the\n// Kinetic App when passing in values\nload.urlParams = [];\n$.each( load.paramsInput, function( key, value ){\n  load.urlParams.push( \"values[\" + encodeURIComponent( key ) + \"]=\" + encodeURIComponent( value ) );\n})\n\n\n// Remove null values from urlParams list\nload.urlParams = load.urlParams.filter(function(val) { return val.split(\"=\")[1]!==\"null\" });\n\n// Load the Subform\nK.load({\n  path: bundle.spaceLocation() + '/'+ K(\"kapp\").slug()+ '/' + load.formSlug + '?' + load.urlParams.join(\"&\"),\n  container: load.container,\n  parent: K('form'),\n  loaded: function(form) {\n    // initialize watch fields definfed in configuration\n\t\t$.each(load.watchFields, function(source, desination){\n\t\t  form.$watch(source, function(newVal,oldVal){\n        K('field['+desination+']').value(newVal);\n      });\n    })\n  }\n});\n",
          "runIf": ""
        },
        {
          "name": "Load Billing Information",
          "type": "Load",
          "action": "Custom",
          "code": "\n// ***** CONFIGURE *********\nvar load = {\n\t//Form to Load\n  \"formSlug\":\"billing-information\", \n  //Container for the form (jQuery syntax)\n  \"container\": '#billingInformation', \n  //Define values to pass into subform.  Map subform Field to value or K('field') reference.\n\t//NOTE: INCLUDE THESE FIELDS IN SUBFORM, OR PAGE WILL NOT LOAD\n  \"paramsInput\": {\n    \"CACN Display\" : K('field[CACN]').value(),\n    \"CACN\" : K('field[CACN]').value(),\n    \"COA\" : K('field[COA]').value(),\n    \"Review Mode\" : K('form').reviewMode() ? true : \"\",\n\t},\n  //Define Fields to set on parent form using watch.  Map subform field to parent form field.\n  \"watchFields\":{\n    \"CACN\": \"CACN\",\n    \"COA\": \"COA\",\n  }\n}\n// ***** END CONFIGURE *********\n\n// Turn paramsInput into formatted/encoded urlParams array as that's what's required by the\n// Kinetic App when passing in values\nload.urlParams = [];\n$.each( load.paramsInput, function( key, value ){\n  load.urlParams.push( \"values[\" + encodeURIComponent( key ) + \"]=\" + encodeURIComponent( value ) );\n})\n\n\n// Remove null values from urlParams list\nload.urlParams = load.urlParams.filter(function(val) { return val.split(\"=\")[1]!==\"null\" });\n\n// Load the Subform\nK.load({\n  path: bundle.spaceLocation() + '/'+ K(\"kapp\").slug()+ '/' + load.formSlug + '?' + load.urlParams.join(\"&\"),\n  container: load.container,\n  parent: K('form'),\n  loaded: function(form) {\n    // initialize watch fields definfed in configuration\n\t\t$.each(load.watchFields, function(source, desination){\n\t\t  form.$watch(source, function(newVal,oldVal){\n        K('field['+desination+']').value(newVal);\n      });\n    })\n  }\n});"
        },
        {
          "name": "Initialize ICWO Table",
          "type": "Load",
          "action": "Custom",
          "code": "// ** ICWO Request **//\n\n/*\n// Configure table and behaviors for Dataviewer\n*/\nsearchConfig = typeof searchConfig===\"object\"? searchConfig : {};\nsearchConfig ={\n  // Example of full configuration of a search object to return results as a DataTable\n  contractTable:{\n    resultsContainer: '<table cellspacing=\"0\", border=\"0\", class=\"display\", style=\"width: 100%;\">',\n\t\tdata: [\n      { \n        title:\"Contract\",\n        name:\"Contract ID\",\n        setField:\"Contract\",\n      }, \n \n      { \n        title:\"Release\",\n        name:\"Contract Release\",\n        setField:\"Contract Release\",\n      },\n      { \n        title:\"Contract Release\",\n        name:\"Contract Rel HNF\",\n        setField:\"Contract Release\",\n      },\n      {\n        title:\"Contract Amount\",\n        name:\"Contract Amount\",\n        setfield:\"Total Amount\",\n      }, \n      { \n        title:\"Contract Amount\",\n        name:\"Contract Amount\",\n        setField:\"Current Contract Amount\",\n        visible: false,\n      }, \n\n      { \n        title:\"Start Date\",\n        name:\"Start Date\",\n        setField:\"Period of Performance - Current Start Date\",\n      }, \n      { \n        title:\"End Date\",\n        name:\"End Date\",\n        setField:\"Period of Performance - Current End Date\",\n      }, \n\t    { \n        title:\"Requesting CACN\",\n        name:\"Req CACN HNF\",\n        setField:\"Requesting CACN\",\n      }, \n\t    { \n        title:\"Performing CACN\",\n        name:\"Perf CACN HNF\",\n        setField:\"Performing CACN\",\n      },\n\t    { \n        title:\"Performing CACN\",\n        name:\"Perf CACN HNF\",\n        setField:\"Performing CACN\",\n      },\n \t    { \n        title:\"Analyst HID\",\n        name:\"Perf Cost Specialist HID\",\n        setField:\"Analyst HID\",\n      },\n \t    { \n        title:\"Analyst Name\",\n        name:\"Perf Cost Specialist Name\",\n        setField:\"Analyst Name\",\n      },\n \t    { \n        title:\"CAM HID\",\n        name:\"Perf WPM HID\",\n        setField:\"CAM HID\",\n      },    \n \t    { \n        title:\"CAM Name\",\n        name:\"Perf WPM Name\",\n        setField:\"CAM Name\",\n      },       \n    ],\n    resultsContainerId: 'contract-table',\n    before: function(configObj){ \n    },\n    success: function (configObj){\n    },\n    successEmpty: function(configObj){\n      // Render the table even if the results are empty. (ie: on page load)\n      configObj.renderer.type(configObj.destination, configObj);\n    },\n    error: function(configObj){\n    },\n    complete: function(configObj){\n    },\n    // Executes on click of element with class of select\n    clickCallback: function(element, results){\n    },\n    removeOnClick: true,\n    renderer: {\n        type: DataViewer.Renderers.DataTables, \n        //type: DataViewer.Renderers.UnorderedList,\n      options: {\n          // Options for Renderer\n          processSingleResult: false,\n          // DataTable OPTIONS; Passing options here make it clear that they are being passed to data tables\n          // responsive: OPTIONAL Default for \"BridgeDataTable\" is true but can be over written.\n          responsive: false,\n          //autoWidth: false,\n          dom: 'rtip',\n          pageLength: 15,\n          paging: false,\n          order: [[1,'desc']]\n          //jsonQuestionField: '', //Define where the JSON Date for the Table is stored\n        },\n    },       \n  },\n}",
          "bridgedResourceName": null
        }
      ],
      "name": "Page 1",
      "renderType": "submittable",
      "type": "page"
    }
  ],
  "securityPolicies": [

  ],
  "slug": "icwo-supplemental",
  "status": "New",
  "submissionLabelExpression": "${form('name')} request for ${values('Requested For Display Name')}",
  "type": "Service"
}